senlin_tempest_plugin/README.rst
senlin_tempest_plugin/__init__.py
senlin_tempest_plugin/base.py
senlin_tempest_plugin/config.py
senlin_tempest_plugin/plugin.py
senlin_tempest_plugin/post_test_hook.sh
senlin_tempest_plugin/pre_test_hook.sh
senlin_tempest_plugin/common/__init__.py
senlin_tempest_plugin/common/clustering_client.py
senlin_tempest_plugin/common/compute_client.py
senlin_tempest_plugin/common/constants.py
senlin_tempest_plugin/common/messaging_client.py
senlin_tempest_plugin/common/network_client.py
senlin_tempest_plugin/common/utils.py
senlin_tempest_plugin/tests/__init__.py
senlin_tempest_plugin/tests/api/__init__.py
senlin_tempest_plugin/tests/api/base.py
senlin_tempest_plugin/tests/api/actions/__init__.py
senlin_tempest_plugin/tests/api/actions/test_action_list.py
senlin_tempest_plugin/tests/api/actions/test_action_list_negative.py
senlin_tempest_plugin/tests/api/actions/test_action_show.py
senlin_tempest_plugin/tests/api/actions/test_action_show_negative.py
senlin_tempest_plugin/tests/api/actions/test_action_update_negative.py
senlin_tempest_plugin/tests/api/api_versions/__init__.py
senlin_tempest_plugin/tests/api/api_versions/test_api_version_show.py
senlin_tempest_plugin/tests/api/api_versions/test_api_version_show_negative.py
senlin_tempest_plugin/tests/api/api_versions/test_api_versions_list.py
senlin_tempest_plugin/tests/api/build_info/__init__.py
senlin_tempest_plugin/tests/api/build_info/test_build_info.py
senlin_tempest_plugin/tests/api/cluster_policies/__init__.py
senlin_tempest_plugin/tests/api/cluster_policies/test_cluster_policy_list.py
senlin_tempest_plugin/tests/api/cluster_policies/test_cluster_policy_list_negative.py
senlin_tempest_plugin/tests/api/cluster_policies/test_cluster_policy_show.py
senlin_tempest_plugin/tests/api/cluster_policies/test_cluster_policy_show_negative.py
senlin_tempest_plugin/tests/api/clusters/__init__.py
senlin_tempest_plugin/tests/api/clusters/test_cluster_action_negative.py
senlin_tempest_plugin-1.8.0.dist-info/AUTHORS
senlin_tempest_plugin-1.8.0.dist-info/LICENSE
senlin_tempest_plugin-1.8.0.dist-info/METADATA
senlin_tempest_plugin-1.8.0.dist-info/WHEEL
senlin_tempest_plugin-1.8.0.dist-info/entry_points.txt
senlin_tempest_plugin-1.8.0.dist-info/pbr.json
senlin_tempest_plugin-1.8.0.dist-info/top_level.txt
senlin_tempest_plugin-1.8.0.dist-info/RECORD
